{
    "marca": "BrooksfieldDonna",
    "catalogo": "Blazers",
    "nome": "Blazer Alfaiataria Transpassado Geralda - Lilas",
    "url": "https://www.brooksdonna.com.br/blazer-alfaiataria-transpassado-geralda-blaf000012qv-41/p",
    "preco_original": "R$1.390,00",
    "preco_final": "R$1.390,00",
    "breadcrumb": "Roupas Lifestyle Categorias Blazer Alfaiataria  Blazer alfaiataria transpassado geralda - lilas",
    "descricao": "",
    "imagem": "https://brooksfielddonna.vtexassets.com/arquivos/ids/193464/BLAF000012QV_41_5-BLAZER-GERALDA.jpg?v=638225352976530000"
}