{
    "marca": "BrooksfieldDonna",
    "catalogo": "Blusa",
    "nome": "Blusa Taylor Tricot Telado - Preto",
    "url": "https://www.brooksdonna.com.br/blusa-taylor-tricot-telado-bbfhtr001ri-17/p",
    "preco_original": "R$690,00",
    "preco_final": "R$690,00",
    "breadcrumb": "Roupas Categorias Blusa  Blusa taylor tricot telado - preto",
    "descricao": "",
    "imagem": "https://brooksfielddonna.vtexassets.com/arquivos/ids/202194/BBFHTR001RI_17_2-BLUSA-TAYLOR-TRICOT-TELADO.jpg?v=638502778790630000"
}