{
    "marca": "BrooksfieldDonna",
    "catalogo": "Blusa",
    "nome": "Blusa Babados Estampada - Estampada",
    "url": "https://www.brooksdonna.com.br/blusa-babados-estampada-bsfs000006rv-12098/p",
    "preco_original": "R$590,00",
    "preco_final": "R$590,00",
    "categoria": "Roupas Categorias Blusa  Blusa babados estampada - estampada",
    "descricao": "",
    "imagem": "https://brooksfielddonna.vtexassets.com/arquivos/ids/198204/BSFS000006RV_12098_4-BLUSA-BABADOS-ESTAMPADA.jpg?v=638349683735200000"
}