{
    "marca": "BrooksfieldDonna",
    "catalogo": "Calça",
    "nome": "Calça Tricot Micro Furos - Preto",
    "url": "https://www.brooksdonna.com.br/calca-tricot-micro-furos-cltr000001qv-17/p",
    "preco_original": "R$690,00",
    "preco_final": "R$690,00",
    "categoria": "Roupas Categorias Calça  Calça tricot micro furos - preto",
    "descricao": "ComposiçãoTecido: 40% Acrílico, 40% Viscose, 20% Poliamida",
    "imagem": "https://brooksfielddonna.vtexassets.com/arquivos/ids/187511/CLTR000001QV_17_4-CALCA-TRICOT-MICRO-FUROS.jpg?v=638005049750470000"
}