{
    "marca": "BrooksfieldDonna",
    "catalogo": "Calça",
    "nome": "Calça Julia - Azul Claro",
    "url": "https://www.brooksdonna.com.br/calca-julia-cfpnaf003ri-31/p",
    "preco_original": "R$1.890,00",
    "preco_final": "R$1.890,00",
    "categoria": "Roupas Categorias Calça  Calça julia - azul claro",
    "descricao": "Composição71% Acetato, 29% Viscose/ Foro de Bolso: 97% Poliéster , 3% Elastano",
    "imagem": "https://brooksfielddonna.vtexassets.com/arquivos/ids/202284/CFPNAF003RI_31_3-CALCA-JULIA.jpg?v=638502791077330000"
}