{
    "marca": "BrooksfieldDonna",
    "catalogo": "Camisa",
    "nome": "Camisa Alfaiataria Canclini Eduarda - Branco",
    "url": "https://www.brooksdonna.com.br/camisa-alfaiataria-canclini-eduarda-ceaf000005pv-004/p",
    "preco_original": "R$540,00",
    "preco_final": "R$540,00",
    "breadcrumb": "Roupas Categorias Camisa  Camisa alfaiataria canclini eduarda - branco",
    "descricao": "",
    "imagem": "https://brooksfielddonna.vtexassets.com/arquivos/ids/168038/CEAF000005PV_004_2-CAMISA-CANCLINI-EDUARDA.jpg?v=637770998788800000"
}