{
    "marca": "BrooksfieldDonna",
    "catalogo": "Casaco",
    "nome": "Jaqueta Couro Bomber Com Botoes - Azul Nevada",
    "url": "https://www.brooksdonna.com.br/jaqueta-couro-bomber-com-botoes-jqcr000001pi-17083/p",
    "preco_original": "R$4.990,00",
    "preco_final": "R$4.990,00",
    "breadcrumb": "Roupas Shop by Categorias Couro Casaco & jaqueta  Jaqueta couro bomber com botoes - azul nevada",
    "descricao": "",
    "imagem": "https://brooksfielddonna.vtexassets.com/arquivos/ids/183029/JQCR000001PI_17083_3-JAQUETA-BOMBER-COURO-C--BOTOES.jpg?v=637872138521870000"
}