{
    "marca": "BrooksfieldDonna",
    "catalogo": "Tshirt",
    "nome": "Polo Tricot Lurex C/ Botões - Ouro Claro",
    "url": "https://www.brooksdonna.com.br/polo-tricot-lurex-c-botoes-bbtr000001rv-13014/p",
    "preco_original": "R$490,00",
    "preco_final": "R$490,00",
    "breadcrumb": "Roupas Categorias T-shirt & regata  Polo tricot lurex c/ botões - ouro claro",
    "descricao": "",
    "imagem": "https://brooksfielddonna.vtexassets.com/arquivos/ids/200082/BBTR000001RV_13014_3-POLO-TRICOT-LUREX-C--BOTOES.jpg?v=638380139524170000"
}