{
    "marca": "BrooksfieldDonna",
    "catalogo": "Shorts",
    "nome": "Shorts Fashion Curto Linho Com Prega - Areia",
    "url": "https://www.brooksdonna.com.br/shorts-fashion-curto-linho-com-prega-shfs000001rv-12/p",
    "preco_original": "R$790,00",
    "preco_final": "R$790,00",
    "breadcrumb": "Roupas Categorias Shorts  Shorts fashion curto linho com prega - areia",
    "descricao": "",
    "imagem": "https://brooksfielddonna.vtexassets.com/arquivos/ids/204991/SHFS000001RV_12_4-SHORTS-LINHO-COM-PREGA.jpg?v=638550264351800000"
}