{
    "marca": "BrooksfieldDonna",
    "catalogo": "Shorts",
    "nome": "Shorts Linho Com Prega - Branco",
    "url": "https://www.brooksdonna.com.br/shorts-linho-com-prega-srctcs001ri-01/p",
    "preco_original": "R$790,00",
    "preco_final": "R$790,00",
    "breadcrumb": "Roupas Categorias Shorts  Shorts linho com prega - branco",
    "descricao": "",
    "imagem": "https://brooksfielddonna.vtexassets.com/arquivos/ids/202621/SRCTCS001RI_01_3-SHORTS-LINHO-COM-PREGA.jpg?v=638502838746770000"
}