{
    "marca": "BrooksfieldDonna",
    "catalogo": "Tshirt",
    "nome": "Top Tricot Busto Recortado - Off White",
    "url": "https://www.brooksdonna.com.br/top-tricot-busto-recortado-tptr000001rv-44/p",
    "preco_original": "R$490,00",
    "preco_final": "R$490,00",
    "breadcrumb": "Roupas Novidades Shop by Lifestyle Categorias Tricot Casual T-shirt & regata  Top tricot busto recortado - off white",
    "descricao": "",
    "imagem": "https://brooksfielddonna.vtexassets.com/arquivos/ids/198351/TPTR000001RV_44_4-TOP-TRICOT-BUSTO-RECORTADO.jpg?v=638349684595230000"
}