{
    "marca": "BrooksfieldDonna",
    "catalogo": "Vestido",
    "nome": "Vestido Longo Jersey C/ Torção - Gold",
    "url": "https://www.brooksdonna.com.br/vestido-longo-jersey-c-torcao-vsmf000006qv-1289/p",
    "preco_original": "",
    "preco_final": "",
    "categoria": "Roupas Categorias Vestido & macacão  Vestido longo jersey c/ torção - gold",
    "descricao": "",
    "imagem": "https://brooksfielddonna.vtexassets.com/arquivos/ids/194756/VSMF000006QV_1289_4-VESTIDO-LONGO-JERSEY-C--TORCAO.jpg?v=638225361261300000"
}