{
    "marca": "LeLis",
    "catalogo": "shorts",
    "nome": "BERMUDA LE LIS LUCY II ALFAIATARIA FEMININA",
    "url": "https://www.lelis.com.br/bermuda-le-lis-lucy-ii-alfaiataria-feminina-17-01-1380-p2187576",
    "preco_original": "R$ 179,90",
    "preco_final": "R$ 889,90",
    "breadcrumb": "Página Inicial Feminino Roupas Bermuda",
    "descricao": " Azul é a escolha perfeita para um look sofisticado e suave. A Bermuda Lucy traz o frescor para o verão, além de adicionar elegância e um toque atemporal na produção. Use com acessórios poderosos, o blazer da mesma coleção e scarpin nos pés, para um resultado charmoso e contemporâneo.A Bermuda é confeccionada em tecido plano com toque de linho, possui modelagem de alfaiataria, caimento reto, cós com passantes e faixa, fechamento frontal por zíper, quatro bolsos e acabamento pespontado. A peça acompanha faixa do mesmo tecido.Composição:55% Linho 45% ViscoseCor: Azul  Este produto pode ser visualizado em 3D e em Realidade Aumentada, clicando no ícone da imagem ao lado.  ",
    "imagem": "https://d1ug6lpn0d6ze6.cloudfront.net/Custom/Content/Products/21/87/2187576_bermuda-lucy-ii-17-01-1380_m1_638518818478114833.jpg"
}