{
    "marca": "LeLis",
    "catalogo": "blazers",
    "nome": "BLAZER LE LIS NITTA ALFAIATARIA FEMININO",
    "url": "https://www.lelis.com.br/blazer-le-lis-nitta-alfaiataria-feminino-21-11-0333-p2118461",
    "preco_original": "R$ 1.480,00",
    "preco_final": "R$ 888,00",
    "breadcrumb": "Página Inicial Feminino Roupas Blazer",
    "descricao": " Peça infalível, o blazer é perfeito para dar um toque final na produção trazendo sofisticação. Invista no conjunto alfaiataria combinando com mix de acessórios e sandálias de salto para um visual elegante e poderoso.O Blazer é confeccionado em malha com modelagem alfaiataria, possui decote V, pences frontais, bolsos frontais embutidos, cintura com passantes, pala posterior sobreposta, mangas longas, forro embutido, fenda posterior e comprimento alongado. Peça acompanha faixa de mesmo tecido para amarração.Composição:100% PoliésterForro: 95% Poliéster 5% ElastanoForro de Bolso: 95% Poliéster 5% ElastanoEntretela: 100% PoliésterCor: Preto  Este produto pode ser visualizado em 3D e em Realidade Aumentada, clicando no ícone da imagem ao lado.  ",
    "imagem": "https://d1ug6lpn0d6ze6.cloudfront.net/Custom/Content/Products/21/18/2118461_blazer-le-lis-nitta-feminino-21-11-0333_m4_638206217764388183.jpg"
}