{
    "marca": "LeLis",
    "catalogo": "calcas",
    "nome": "CALÇA LE LIS CONY FEMININA",
    "url": "https://www.lelis.com.br/calca-le-lis-cony-feminina-18-12-1385-p2128148",
    "preco_original": "R$ 689,90",
    "preco_final": "R$ 275,96",
    "breadcrumb": "Página Inicial Feminino Roupas Calça",
    "descricao": " Invista em peças confortáveis com cores neutras para produzir diversos looks. Experimente usar a Calça Cony com a blusa da mesma coleção, formando um twin set monocromático, acessórios e papetes. A produção fica contemporânea, perfeita para o dia a dia com mobilidade.Confeccionada em malha, a Calça possui cintura alta, cós largo, barra com pregas e detalhe de botões triplos, acabamento em pespontos contrastantes.Composição:38,99% Poliamida 19,75% Viscose 16,50% Poliéster 13,04% Algodão 6,72% Linho 5% ElastanoCor: Bege Claro  Este produto pode ser visualizado em 3D e em Realidade Aumentada, clicando no ícone da imagem ao lado.  ",
    "imagem": "https://d1ug6lpn0d6ze6.cloudfront.net/Custom/Content/Products/21/28/2128148_calca-le-lis-cony-feminina-18-12-1385_m1_638265081964639087.jpg"
}