{
    "marca": "LeLis",
    "catalogo": "calcas",
    "nome": "CALÇA LE LIS STELLA SKINNY I ALFAIATARIA FEMININA",
    "url": "https://www.lelis.com.br/calca-le-lis-stella-skinny-i-alfaiataria-feminina-18-12-1323-p2080255",
    "preco_original": "R$ 889,90",
    "preco_final": "R$ 789,90",
    "breadcrumb": "Página Inicial Feminino Roupas Calça",
    "descricao": " Alfaiataria é uma ótima escolha, por se encaixar muito bem tanto em eventos formais quanto aos mais descontraídos. Use a Calça Stella em um look all black com top, sandálias flats, acessórios metalizados e o blazer da mesma coleção para arrematar.A Calça é confeccionada em tecido plano com modelagem alfaiataria, possui modelagem skinny, cós com passantes, fechamento frontal com botão e zíper, detalhe de vinco e acabamento pespontado.Composição: 70% Poliéster 30% ViscoseForro: 100% PoliésterCor: Preto  Este produto pode ser visualizado em 3D e em Realidade Aumentada, clicando no ícone da imagem ao lado.  ",
    "imagem": "https://d1ug6lpn0d6ze6.cloudfront.net/Custom/Content/Products/20/80/2080255_calca-le-lis-stella-skinny-i-alfaiataria-feminina-18-12-1323_m21_638543251567964682.jpg"
}