{
    "marca": "LeLis",
    "catalogo": "calcas",
    "nome": "CALÇA SALOPETE LE LIS ALINE ALFAIATARIA FEMININA",
    "url": "https://www.lelis.com.br/calca-salopete-le-lis-aline-alfaiataria-feminina-18-11-2677-p2161843",
    "preco_original": "R$ 1.180,00",
    "preco_final": "R$ 590,00",
    "breadcrumb": "Página Inicial Feminino Roupas Calça",
    "descricao": " A alfaiataria permanece sendo um investimento duradouro em estilo, além de transitar em diversas ocasiões. Combine com mix de acessórios dourados, blusa e finalize com sandália de salto, para um visual charmoso e poderoso.A Calça é confeccionada em tecido plano, possui modelagem de alfaiataria, cós com bolsos embutidos e recorte frontal, fechamento frontal por zíper, quatro bolsos e acabamento pespontado.Composição: 100% PoliésterCor: Preto  Este produto pode ser visualizado em 3D e em Realidade Aumentada, clicando no ícone da imagem ao lado.  ",
    "imagem": "https://d1ug6lpn0d6ze6.cloudfront.net/Custom/Content/Products/21/61/2161843_calca-le-lis-salopete-aline-feminina-18-11-2677_m1_638418785652441984.jpg"
}