{
    "marca": "LeLis",
    "catalogo": "calcas",
    "nome": "CALÇA LE LIS PANTACOURT EVE ALFAIATARIA FEMININA",
    "url": "https://www.lelis.com.br/calca-le-lis-pantacourt-eve-alfaiataria-feminina-18-11-2570-p2148013",
    "preco_original": "R$ 889,90",
    "preco_final": "R$ 444,95",
    "breadcrumb": "Página Inicial Feminino Roupas Calça",
    "descricao": " A Calça Eve traz a modernidade em sua alfaiataria, criando produções neutras e versáteis. Combine com argola, regata e complemente com sandália rasteira, para um visual casual all white elegante.A Calça é confeccionada em tecido plano com toque de linho, possui modelagem alfaiataria, cós com passantes, bolsos frontais e posteriores, fechamento frontal, cordão para amarração e acabamento pespontado. A peça acompanha cordão do mesmo tecido.Composição: 40% Poliéster 35% Linho 25% ViscoseCor: Off White  Este produto pode ser visualizado em 3D e em Realidade Aumentada, clicando no ícone da imagem ao lado.  ",
    "imagem": "https://d1ug6lpn0d6ze6.cloudfront.net/Custom/Content/Products/21/48/2148013_calca-le-lis-pantacourt-eve-alfaiataria-feminina-18-11-2570_m2_638344454240372243.jpg"
}