{
    "marca": "LeLis",
    "catalogo": "calcas",
    "nome": "CALÇA LE LIS BARBATANA VIVI FEMININA",
    "url": "https://www.lelis.com.br/calca-le-lis-barbatana-vivi-feminina-18-12-1377-p2126566",
    "preco_original": "R$ 989,90",
    "preco_final": "R$ 395,96",
    "breadcrumb": "Página Inicial Feminino Roupas Calça",
    "descricao": " A alfaiataria está presente em todas as estações para elevar o seu visual com elegância,aproveite a versatilidade da cor preta na Calça Vivi, que fica incrível quando é combinadacom blusa de paetê, acessórios e sandálias de salto. O resultado é uma produção trendychic impecável para eventos.Confeccionada em tecido plano commodelagem alfaiataria, a Calça possui caimento reto, cintura alta, cós com detalhe de barbatanas aplicadas, pregas e bolsos frontais, bolsos posteriores embutidos, fechamento na lateral por zíper invisívele acabamento pespontado.Composição: 88% Poliéster 12% ElastanoForro do Bolso: 95% Poliéster 5% ElastanoCor: Preto  Este produto pode ser visualizado em 3D e em Realidade Aumentada, clicando no ícone da imagem ao lado.  ",
    "imagem": "https://d1ug6lpn0d6ze6.cloudfront.net/Custom/Content/Products/21/26/2126566_calca-le-lis-barbatana-vivi-feminina-18-12-1377_m5_638243228001104758.jpg"
}