{
    "marca": "LeLis",
    "catalogo": "camisa",
    "nome": "CAMISA LE LIS SAMANTHA FEMININA",
    "url": "https://www.lelis.com.br/camisa-le-lis-samantha-feminina-13-01-6227-p2191339",
    "preco_original": "R$ 689,90",
    "preco_final": "R$ 589,90",
    "breadcrumb": "Página Inicial Feminino Roupas Camisa",
    "descricao": " Uma aposta segura de estilo e modernidade, a Camisa Samantha é versátil e irá renovar seus looks. Combine com acessórios dourados, saia da mesma coleção e complemente com sandália rasteira, para um visual easychic.A Camisa é confeccionada em tecido plano, possui gola com colarinho, mangas curtas, bolsos amplos com lapelas e botões, fechamento frontal por botões, comprimento curto e acabamento pespontado.Composição: 100% AlgodãoCor: Bege ClaroEsta peça possui o algodão como principal matéria-prima e representa o apoio da Le Lis ao movimentoSou de Algodão– iniciativa que destaca ao consumidor a importância do cultivo da fibra no Brasil promovendo a responsabilidade social e ambiental.  Este produto pode ser visualizado em 3D e em Realidade Aumentada, clicando no ícone da imagem ao lado.  ",
    "imagem": "https://d1ug6lpn0d6ze6.cloudfront.net/Custom/Content/Products/21/91/2191339_camisa-le-lis-samantha-feminina-13-01-6227_m1_638544041083171456.jpg"
}