{
    "marca": "LeLis",
    "catalogo": "camisa",
    "nome": "CAMISA LE LIS ROLOTE VIENNA FEMININA",
    "url": "https://www.lelis.com.br/camisa-le-lis-rolote-vienna-feminina-13-01-6179-p2172469",
    "preco_original": "R$ 639,90",
    "preco_final": "R$ 383,94",
    "breadcrumb": "Página Inicial Feminino Roupas Camisa",
    "descricao": " Peça crucial para conforto e elegância, além de garantir um caimento impecável ao corpo. Combine com acessórios, calça e finalize com scarpin, para um visual easychic e poderoso.A Camisa é confeccionada em tecido plano, possui gola colarinho, bolso frontal, mangas longas com abotoamento nos punhos, detalhes franzidos, cordão aplicado para amarração, fechamento frontal por botões e acabamento pespontado.Composição: 100% AlgodãoCor: Branco  Este produto pode ser visualizado em 3D e em Realidade Aumentada, clicando no ícone da imagem ao lado.  ",
    "imagem": "https://d1ug6lpn0d6ze6.cloudfront.net/Custom/Content/Products/21/72/2172469_camisa-le-lis-rolote-vienna-feminina-13-01-6179_m1_638464638743764624.jpg"
}