{
    "marca": "LeLis",
    "catalogo": "camisa",
    "nome": "CAMISA LE LIS BECK I FEMININA",
    "url": "https://www.lelis.com.br/camisa-le-lis-beck-i-feminina-13-75-0097-p2189673",
    "preco_original": "R$ 589,90",
    "preco_final": "R$ 589,90",
    "breadcrumb": "Página Inicial Feminino Roupas Camisa",
    "descricao": " Com estilo e sofisticação traduzem facilmente a Camisa Beck, além de compor looks infalíveis. Combine com mix de acessórios, calça jeans e finalize com sandália, para arrematar.A Camisa é confeccionada em linho, possui gola com colarinho, decote V, mangas 7/8 com volume bufante e elásticos nos punhos, fechamento frontal por botões e acabamento pespontado.Composição: 100% LinhoCor: Azul Claro  Este produto pode ser visualizado em 3D e em Realidade Aumentada, clicando no ícone da imagem ao lado.  ",
    "imagem": "https://d1ug6lpn0d6ze6.cloudfront.net/Custom/Content/Products/21/89/2189673_camisa-le-lis-beck-i-feminina-13-75-0097_m1_638530298851860816.jpg"
}