{
    "marca": "LeLis",
    "catalogo": "macacao",
    "nome": "MACACÃO LE LIS BARBARA FEMININO",
    "url": "https://www.lelis.com.br/macacao-le-lis-barbara-feminino-07-11-0349-p2146923",
    "preco_original": "R$ 489,90",
    "preco_final": "R$ 244,95",
    "breadcrumb": "Página Inicial Feminino Roupas Macacão",
    "descricao": " A melhor escolha são peças únicas para compor o look em minutos, aposte no Macacão Barbara para arrasar no look all black. Combine com brincos, cinto, papetes e finalize com bolsa, para um visual easy chic.O Macacão é confeccionado em malha, possui decote redondo, alças largas, recorte vazado, fechamento posterior por zíper, comprimento longo e acabamento pespontado.Composição: 98% Viscose 2% ElastanoCor: Preto  Este produto pode ser visualizado em 3D e em Realidade Aumentada, clicando no ícone da imagem ao lado.  ",
    "imagem": "https://d1ug6lpn0d6ze6.cloudfront.net/Custom/Content/Products/21/46/2146923_macacao-le-lis-barbara-feminino-07-11-0349_m9_638344361019411512.jpg"
}