{
    "marca": "LeLis",
    "catalogo": "macacao",
    "nome": "MACACÃO LE LIS ROSY FEMININO",
    "url": "https://www.lelis.com.br/macacao-le-lis-rosy-feminino-07-04-0334-p2196457",
    "preco_original": "R$ 889,90",
    "preco_final": "R$ 889,90",
    "breadcrumb": "Página Inicial Feminino Roupas Macacão",
    "descricao": " Encante-se com a elegância e sofisticação do Macacão Rosy, peça indispensável no closet de quem busca estilo e conforto. Experimente com mix de acessórios dourados e complemente com sapatilha, para um look moderno e chic.O Macacão é confeccionado em tecido plano com toque de linho, possui gola com colarinho, mangas longas com abotoamento nos punhos, bolsos frontais e posteriores, fechamento frontal por botões, comprimento curto e acabamento pespontado.Composição: 55% Linho 45% ViscoseCor: Azul Marinho  Este produto pode ser visualizado em 3D e em Realidade Aumentada, clicando no ícone da imagem ao lado.  ",
    "imagem": "https://d1ug6lpn0d6ze6.cloudfront.net/Custom/Content/Products/21/96/2196457_macacao-le-lis-rosy-feminino-07-04-0334_m7_638566357702793494.jpg"
}