{
    "marca": "LeLis",
    "catalogo": "casaco",
    "nome": "PARKA LE LIS ANA FEMININA",
    "url": "https://www.lelis.com.br/parka-le-lis-ana-feminina-23-04-0463-p2120778",
    "preco_original": "R$ 1.380,00",
    "preco_final": "R$ 552,00",
    "breadcrumb": "Página Inicial Feminino Roupas Casacos",
    "descricao": " Escolha peças bordadas para elevar a produção com sofisticação e feminilidade. Aposte naParka Ana combinando com um top de tricot, calça jeans e flats, para uma produção autêntica e ideal para saídas descontraídas.A Parka é confeccionada em sarja com padronagem animal print, possui detalhe frontal de bordados, gola com colarinho, fechamento frontal por botões, bolsos frontais com lapelas, cintura com elástico aplicado, mangas longas e acabamento pespontado.Composição: 100% AlgodãoCor: Estampado  Este produto pode ser visualizado em 3D e em Realidade Aumentada, clicando no ícone da imagem ao lado.  ",
    "imagem": "https://d1ug6lpn0d6ze6.cloudfront.net/Custom/Content/Products/21/20/2120778_parka-le-lis-ana-feminina-23-04-0463_m12_638265042643626729.jpg"
}