{
    "marca": "LeLis",
    "catalogo": "casaco",
    "nome": "PARKA LE LIS KAKA FEMININA",
    "url": "https://www.lelis.com.br/parka-le-lis-kaka-feminina-23-11-2361-p2170664",
    "preco_original": "R$ 119,90",
    "preco_final": "R$ 989,90",
    "breadcrumb": "Página Inicial Feminino Roupas Casacos",
    "descricao": " Escolha excelente para complementar seu visual em dias de temperatura amenas, além de garantir conforto e sofisticação. Combine com acessórios, regata, calça da mesma coleção e finalize com bota, para arrematar.A Parka é confeccionada em nylon, possui gola alta, bolsos frontais, elásticos ajustáveis, mangas longas com abotoamento nos punhos, fechamento frontal por zíper e botões e acabamento pespontado.Composição: 100% PoliésterCor: Azul Marinho  Este produto pode ser visualizado em 3D e em Realidade Aumentada, clicando no ícone da imagem ao lado.  ",
    "imagem": "https://d1ug6lpn0d6ze6.cloudfront.net/Custom/Content/Products/21/70/2170664_parka-le-lis-kaka-feminina-23-11-2361_m1_638470682060456913.jpg"
}