{
    "marca": "LeLis",
    "catalogo": "regatas",
    "nome": "REGATA LE LIS BIBI II TRICOT FEMININA",
    "url": "https://www.lelis.com.br/regata-le-lis-bibi-ii-tricot-feminina-12-04-1534-p2147249",
    "preco_original": "R$ 489,90",
    "preco_final": "R$ 293,94",
    "breadcrumb": "Página Inicial Feminino Roupas Regata",
    "descricao": " Peça essencial para uma produção em minutos, a Regata Bibi é versátil e perfeita para várias ocasiões. Combine com mix de acessórios dourados, shorts e complemente com papetes, para um visual leve e chic.A Regata é confeccionada em tricot, possui pedrarias aplicadas, decote V, alças médias e acabamento canelado.Composição: 70% Viscose 30% PoliamidaCor: Off White  Este produto pode ser visualizado em 3D e em Realidade Aumentada, clicando no ícone da imagem ao lado.  ",
    "imagem": "https://d1ug6lpn0d6ze6.cloudfront.net/Custom/Content/Products/21/47/2147249_regata-le-lis-bibi-ii-tricot-feminina-12-04-1534_m7_638344377601395573.jpg"
}