{
    "marca": "LeLis",
    "catalogo": "saia",
    "nome": "SAIA LE LIS SAMANTA MIDI FEMININA",
    "url": "https://www.lelis.com.br/saia-samanta-16-04-1106-p2184457",
    "preco_original": "R$ 589,90",
    "preco_final": "R$ 589,90",
    "breadcrumb": "Página Inicial Feminino Roupas Saia",
    "descricao": " Proporcionando um charme extra ao seu visual, a Saia Samanta garante diversas combinações. Combine com mix de acessórios, blusa off white, scarpin metalizado e finalize com bolsa, para um look easychic.A Saia é confeccionada em malha, possui cós aplicado, bolsos frontais, fenda frontal, fechamento lateral por zíper invisível, comprimento midi e acabamento pespontado.Composição: 65% Viscose 30% Poliamida 5%ElastanoCor: Preto  Este produto pode ser visualizado em 3D e em Realidade Aumentada, clicando no ícone da imagem ao lado.  ",
    "imagem": "https://d1ug6lpn0d6ze6.cloudfront.net/Custom/Content/Products/21/84/2184457_saia-samanta-16-04-1106_m1_638503184780234388.jpg"
}