{
    "marca": "LeLis",
    "catalogo": "saia",
    "nome": "SAIA LE LIS ANA LAURA TRICOT FEMININA",
    "url": "https://www.lelis.com.br/saia-le-lis-ana-laura-tricot-feminina-16-19-0316-p2156083",
    "preco_original": "R$ 689,90",
    "preco_final": "R$ 344,95",
    "breadcrumb": "Página Inicial Feminino Roupas Saia",
    "descricao": " Para compor uma produção infalível e cheia de estilo, a Saia Ana Laura é a peça ideal para você. Combine com mix de acessórios, top da mesma coleção e finalize com sandália rasteira, para um visual poderoso e sofisticado.A Saia é confeccionada em tricot, possui cintura alta, cós aplicado, detalhes de mini vazados, babado aplicado, comprimento midi e acabamento canelado.Composição: 66% Poliéster 34% PolipropilenoCor: Listrado  Este produto pode ser visualizado em 3D e em Realidade Aumentada, clicando no ícone da imagem ao lado.  ",
    "imagem": "https://d1ug6lpn0d6ze6.cloudfront.net/Custom/Content/Products/21/56/2156083_saia-le-lis-ana-laura-tricot-feminina-16-19-0316_m8_638429828688416439.jpg"
}