{
    "marca": "LeLis",
    "catalogo": "saia",
    "nome": "SAIA LE LIS BRUNA MIDI FEMININA",
    "url": "https://www.lelis.com.br/saia-le-lis-bruna-midi-feminina-16-11-2310-p2137037",
    "preco_original": "R$ 889,90",
    "preco_final": "R$ 355,96",
    "breadcrumb": "Página Inicial Feminino Roupas Saia",
    "descricao": " As peças de tecido plano garante um visual elegante na produção. Invista na Saia Bruna usando com acessórios dourados e sandálias de salto, para um mood chic e poderoso.A Saia é confeccionada em tecido plano com fios de lurex e efeito dourado, possui modelagem envelope, caimento reto, fechamento posterior por zíper invisível e acabamento pespontado.Composição: 100% PoliésterCor: Preto  Este produto pode ser visualizado em 3D e em Realidade Aumentada, clicando no ícone da imagem ao lado.  ",
    "imagem": "https://d1ug6lpn0d6ze6.cloudfront.net/Custom/Content/Products/21/37/2137037_saia-bruna-16-11-2310_m6_638303028107655099.jpg"
}