{
    "marca": "LeLis",
    "catalogo": "regatas",
    "nome": "TOP LE LIS OMBRO SO VIVIAN FEMININO",
    "url": "https://www.lelis.com.br/top-le-lis-ombro-so-vivian-feminino-08-01-0221-p2157500",
    "preco_original": "R$ 789,90",
    "preco_final": "R$ 473,94",
    "breadcrumb": "Página Inicial Feminino Roupas Top Feminino",
    "descricao": " Para valorizar ainda mais sua produção, aposte peças de linho para um visual fresh e cheio de atitude. Use com mix de acessórios dourados, saia e finalize com sandália de salto, para um look monocromático poderoso.O Top é confeccionado em linho, possui decote um ombro só, manga 2/3 levemente bufante e acabamento pespontado.Composição: 100% LinhoCor: Rosa Médio  Este produto pode ser visualizado em 3D e em Realidade Aumentada, clicando no ícone da imagem ao lado.  ",
    "imagem": "https://d1ug6lpn0d6ze6.cloudfront.net/Custom/Content/Products/21/57/2157500_top-le-lis-ombro-so-vivian-feminino-08-01-0221_m2_638415406532681250.jpg"
}