{
    "marca": "LeLis",
    "catalogo": "vestido",
    "nome": "VESTIDO LE LIS MABI I MIDI FEMININO",
    "url": "https://www.lelis.com.br/vestido-le-lis-mabi-i-midi-feminino-15-11-4499-p2191573",
    "preco_original": "R$ 689,90",
    "preco_final": "R$ 589,90",
    "breadcrumb": "Página Inicial Feminino Roupas Vestido",
    "descricao": " Um clássico do conforto, desfrute de uma malha de qualidade que permita movimento, sem deixar o estilo e a autenticidade de lado. Use o Vestido Mabi com acessórios poderosos e flats, para um visual elegante e confortável.O Vestido é confeccionado em malha, possui caimento acinturado, decote em “V” profundo, mangas curtas amplas, detalhe frontal de pregas, comprimento midi e acabamento pespontado.Composição: 98% Viscose 2% ElastanoCor: Verde Militar  Este produto pode ser visualizado em 3D e em Realidade Aumentada, clicando no ícone da imagem ao lado.  ",
    "imagem": "https://d1ug6lpn0d6ze6.cloudfront.net/Custom/Content/Products/21/91/2191573_vestido-le-lis-mabi-i-midi-feminino-15-11-4499_m1_638537914560521510.jpg"
}