{
    "marca": "LeLis",
    "catalogo": "vestido",
    "nome": "VESTIDO LE LIS ELBA II FEMININO",
    "url": "https://www.lelis.com.br/vestido-le-lis-elba-ii-feminino-15-02-0482-p2158266",
    "preco_original": "R$ 889,90",
    "preco_final": "R$ 444,95",
    "breadcrumb": "Página Inicial Feminino Roupas Vestido",
    "descricao": " Na busca por peças charmosas e femininas aposte no Vestido Elba que proporciona elegância e um toque fresh para o visual. Combine com acessórios dourados e sandália de salto, para arrematar.O Vestido é confeccionado tecido plano, possui modelagem levemente evasê, decote ombro a ombro com detalhes franzidos, mangas bufantes 3/4, faixa na cintura para amarração, barra com babado e entremeios, comprimento midi e acabamento pespontado.Composição: 97% Algodão 3% ElastanoCor: Roxo Claro  Este produto pode ser visualizado em 3D e em Realidade Aumentada, clicando no ícone da imagem ao lado.  ",
    "imagem": "https://d1ug6lpn0d6ze6.cloudfront.net/Custom/Content/Products/21/58/2158266_vestido-le-lis-elba-ii-feminino-15-02-0482_m1_638409161405701938.jpg"
}