{
    "marca": "Alcaçuz",
    "catalogo": "blusas",
    "nome": "BLUSA DECOTE V PRISCILA",
    "url": "https://www.alcacuz.com.br/blusa-priscila-4z48169a6.html",
    "preco_original": "R$ 990,00",
    "preco_final": "R$ 594,00",
    "breadcrumbs": "Início  BLUSA DECOTE V PRISCILA",
    "descricao": "Blusa Priscila, Alcaçuz. Confeccionada em Ponto de Roma, um tecido encorpado e com boa elasticidade à base de viscose. Possui modelagem reta e ampla estilo oversized, decote amplo em 'V', mangas 3/4 com punhos alongados, fendas inferiores, recortes aparentes, acabamento pespontado clássico e comprimento regular.",
    "imagem": "https://cdn.alcacuz.com.br/catalog/product/cache/3502ee8959faa2d833da390666aee523/a/l/alca_uz_2394.jpg"
}