{
    "marca": "Alcaçuz",
    "catalogo": "calcas",
    "nome": "CALÇA DE ELÁSTICO PAIOL",
    "url": "https://www.alcacuz.com.br/calca-paiol-7d48015v9.html",
    "preco_original": "R$ 1.280,00",
    "preco_final": "R$ 768,00",
    "breadcrumbs": "Início  CALÇA DE ELÁSTICO PAIOL",
    "descricao": "Calça Paiol, Alcaçuz. Confeccionada em tecido leve. Possui modelagem reta, cintura média, cós reto com elasticidade interna para melhor ajuste ao corpo, dois bolsos laterais funcionais, dois bolsos embutidos posteriores, recortes geométricos aparentes, barras ligeiramente afuniladas com pregueado lateral, acabamento pespontado clássico e comprimento regular.",
    "imagem": "https://cdn.alcacuz.com.br/catalog/product/cache/3502ee8959faa2d833da390666aee523/7/d/7d48015v9_1_.jpg"
}