{
    "marca": "Alcaçuz",
    "catalogo": "casacos",
    "nome": "JAQUETA METALIZADA PESSOA",
    "url": "https://www.alcacuz.com.br/jaqueta-pessoa-7r48126o9.html",
    "preco_original": "R$ 1.990,00",
    "preco_final": "R$ 995,00",
    "breadcrumbs": "Início  JAQUETA METALIZADA PESSOA",
    "descricao": "Jaqueta Pessoa, Alcaçuz. Confeccionada em tecido leve à base de viscose e algodão. Possui modelagem reta e ligeiramente acinturada, gola alta arredondada, mangas longas, punhos estruturados com abotoamento lateral, elasticidade central com regulagem dupla, dois bolsos frontais com abas para fechamento, fendas laterais com abotoamento por botões metálicos envelhecidos, barrado inferior com elasticidade interna e regulagens frontais, acabamento metalizado total, finalização pespontada clássica, comprimento regular e fechamento frontal por zíper com puxadores.",
    "imagem": "https://cdn.alcacuz.com.br/catalog/product/cache/3502ee8959faa2d833da390666aee523/7/r/7r48126o9_2_.jpg"
}