{
    "marca": "Alcaçuz",
    "catalogo": "saias",
    "nome": "SAIA ALGODÃO SABRINA",
    "url": "https://www.alcacuz.com.br/saia-algodao-sabrina-is49004pp.html",
    "preco_original": "R$ 1.780,00",
    "preco_final": "R$ 1.780,00",
    "breadcrumbs": "Início  SAIA ALGODÃO SABRINA",
    "descricao": "A Saia Sabrina possui modelagem reta oferece um toque de sofisticação e praticidade, sendo ideal para viver momentos especiais. Com bolsos laterais amplos e aparentes, proporciona funcionalidade e um design moderno. O zíper frontal e os passantes garantem praticidade ao vestir, enquanto o cinto com pesponto aparente no mesmo tecido adiciona um detalhe elegante e exclusivo à peça. A Saia Sabrina é perfeita para quem busca uma peça versátil que combina charme e exclusividade. Veja mais benefícios:- Saia reta para um visual sofisticado- Bolsos laterais amplos e aparentes para funcionalidade e estilo- Zíper frontal para praticidade ao vestir- Passantes e cinto com pesponto aparente para um toque elegante",
    "imagem": "https://cdn.alcacuz.com.br/catalog/product/cache/3502ee8959faa2d833da390666aee523/i/s/is49004pp_1.jpg"
}