{
    "marca": "NV",
    "catalogo": "Shorts",
    "nome": "Bermuda Loretta - Vermelho Ameixa",
    "url": "https://www.bynv.com.br/bermuda-loretta-vermelho-ameixa-v252232-nv370/p",
    "preco_original": "",
    "preco_final": "",
    "breadcrumb": "New In",
    "descricao": "Bermuda de cintura média em crepe de alfaiataria com modelagem oversized. Possui pregas tombadas, passantes duplos, bolsos faca frontais e besom na parte de trás, seu fechamento é por zíper, colchete e botão de segurança.",
    "imagem": "https://bynv.vtexassets.com/arquivos/ids/613616-856-1284/V252232_NV370_1-BERMUDA-LORETTA.jpg?v=638567687014570000"
}