{
    "marca": "Animale",
    "catalogo": "blusa",
    "nome": "Blusa De Georgette Um Ombro Estampado",
    "url": "https://www.animale.com.br/blusa-de-georgette-um-ombro-estampado-est-pois-tri-preto-e-exotique-52-13-5326-09563/p",
    "preco_original": "R$598,00",
    "preco_final": "R$598,00",
    "breadcrumb": "Home New Collection Top/Blusa",
    "descricao": "Proposta leve e sofisticada para os dias de verão, a Blusa de Georgette traz uma combinação rica de detalhes para compor diversos looks. O modelo de um ombro só possui forro, comprimento clássico, alça drapeada e regulagem por amarração no ombro, adicionando fluidez e movimento ao look. A estampa de poás ressalta a feminilidade da produção, enquanto a calça de sarja e os acessórios complementam o look com personalidade e frescor.Detalhes:-Decote um ombro só;-Comprimento clássico;-Alça drapeada;-Regulagem por amarração no ombro.",
    "imagem": "https://lojaanimale.vteximg.com.br/arquivos/ids/1791805-708-1067/52135326_09563_1-BLUSA-DE-GEORGETTE-UM-OMBRO-ESTAMPADO.jpg?v=638556422898530000"
}