{
    "marca": "Animale",
    "catalogo": "calca",
    "nome": "Calça Jeans Wide Leg Raw Denim",
    "url": "https://www.animale.com.br/calca-jeans-wide-leg-raw-denim-jeans-escuro-25-34-1775-0109/p",
    "preco_original": "R$598,00",
    "preco_final": "R$598,00",
    "breadcrumb": "Home New Collection Calça",
    "descricao": "Um clássico, a Calça Jeans Wide Leg surge no verão com lavagem escura e cintura alta. O modelo apresenta fecho por abotoamento, bolsos laterais e traseiros, além de passantes no cós. O encontro das escolhas neutras como o body e os acessórios com a calça jeans, exalta o mood urbano da estação.Detalhes:- Jeans escuro;- Modelagem wide leg;- Bolsos frontais e nas costas;- Fechamento por abotoamento frontal;- Passantes no cós;- Cintura alta.",
    "imagem": "https://lojaanimale.vteximg.com.br/arquivos/ids/1790326-708-1067/25341775_0109_1-CALCA-JEANS-WIDE-LEG-RAW-DENIM.jpg?v=638556415072570000"
}