{
    "marca": "Animale",
    "catalogo": "blusa",
    "nome": "Regata De Couro Botoes Ombro",
    "url": "https://www.animale.com.br/regata-de-couro-botoes-ombro-amarelo-papiro-52-15-1398-01011/p",
    "preco_original": "R$1.698,00",
    "preco_final": "R$1.698,00",
    "breadcrumb": "Home New Collection Top/Blusa",
    "descricao": "Aposta do verão 25, a Regata de Couro é um must-have atemporal, que ganha ares de verão nos novos tons neutros e exclusivos da coleção. Sua modelagem garante durabilidade e conforto em modelo cropped sem mangas, com botões no ombro e recortes com pespontos no mesmo tom amarelo papiro do couro. Um item indispensável para quem não abre mão dos clássicos eternos no closet. O total look de couro, com a calça no mesmo estilo e mule de salto, traz elegância para a rotina urbana.Detalhes:- Sem mangas;- Comprimento cropped;- Decote redondo;- Recortes pespontados;- Botões nos ombros.",
    "imagem": "https://lojaanimale.vteximg.com.br/arquivos/ids/1796651-708-1067/52151398_01011_1-REGATA-DE-COURO-BOTOES-OMBRO.jpg?v=638560777156300000"
}