{
    "marca": "Animale",
    "catalogo": "blusa",
    "nome": "Regata Telada",
    "url": "https://www.animale.com.br/regata-telada-bege-gengibre-52-15-1363-6205/p",
    "preco_original": "R$248,00",
    "preco_final": "R$248,00",
    "breadcrumb": "Home New Collection Top/Blusa",
    "descricao": "No Bege Gengibre, cor exclusiva da coleção, a Regata Telada de Tricot atualiza os básicos da estação com comprimento clássico, decote redondo e vivo canelado nos acabamentos. O modelo é essencial no closet e perfeito para complementar produções neutras com cintos sobrepostos.Detalhes:- Tricot telado;- Sem mangas;- Decote redondo;- Não possui forro.",
    "imagem": "https://lojaanimale.vteximg.com.br/arquivos/ids/1792373-708-1067/52151363_6205_1-REGATA-TRANSPARENTE.jpg?v=638556425955970000"
}