{
    "marca": "Animale",
    "catalogo": "blusa",
    "nome": "Top De Couro Sem Alça Recortes",
    "url": "https://www.animale.com.br/top-de-couro-sem-alca-recortes-marrom-rum-52-10-5089-09032/p",
    "preco_original": "R$3.598,00",
    "preco_final": "R$3.598,00",
    "breadcrumb": "Home New Collection Top/Blusa",
    "descricao": "100% Couro",
    "imagem": "https://lojaanimale.vteximg.com.br/arquivos/ids/1790965-708-1067/52105089_09032_1-TOP-DE-COURO-SEM-ALCA-RECORTES.jpg?v=638556418569070000"
}