{
    "marca": "Animale",
    "catalogo": "vestido",
    "nome": "Vestido De Couro Curto Faixa Assimetrica",
    "url": "https://www.animale.com.br/vestido-de-couro-curto-faixa-assimetrica-bege-whitecap-07-20-6584-04346/p",
    "preco_original": "R$6.598,00",
    "preco_final": "R$6.598,00",
    "breadcrumb": "Home New Collection Vestido",
    "descricao": "Aposta do Verão 25, a linha que pulsa nosso DNA traz o Vestido Curto de Couro na paleta fresca e clara da estação. O modelo no tom bege possui faixa assimétrica com regulagem na cintura, decote em V, alças largas, pespontos no mesmo tom do couro, e recorte nas costas com fechamento por botões e zíper. Must-have em todas as estações, o leather look continua se reforçando como ícone da marca.Detalhes:- 100% Couro;- Fechamento por abotoamento e zíper nas costas;- Comprimento curto;- Recorte traseiro;- Sem mangas;- Faixa assimétrica regulável na cintura.",
    "imagem": "https://lojaanimale.vteximg.com.br/arquivos/ids/1786395-708-1067/07206584_04346_1-VESTIDO-DE-COURO-CURTO-FAIXA-ASSIMETRICA.jpg?v=638556372388270000"
}