{
    "marca": "Animale",
    "catalogo": "vestido",
    "nome": "Vestido Longo Com Gola Lenço Bronze",
    "url": "https://www.animale.com.br/vestido-longo-com-gola-lenco-bronze-bronze-07-20-6179-1600/p",
    "preco_original": "R$1.398,00",
    "preco_final": "R$1.398,00",
    "breadcrumb": "Home New Collection Vestido",
    "descricao": "95% Poliamida 5% Elastano",
    "imagem": "https://lojaanimale.vteximg.com.br/arquivos/ids/1785697-708-1067/07206179_1600_1-VESTIDO-LONGO-COM-GOLA-LENCO-BRONZE.jpg?v=638556368259670000"
}