{
    "marca": "Shoulder",
    "catalogo": "Blusa",
    "nome": "Blusa reta decote v",
    "url": "https://www.shoulder.com.br/blusa-reta-decote-v-242011913/p",
    "preco_original": "R$379,00",
    "preco_final": "R$379,00",
    "breadcrumbs": "coleção blusas",
    "descricao": "Blusa Comprimento médio Manga longa Modelagem reta Tecido: Alfaiataria encorpada com elasticidade Decote V Punho com botão forrado Fendas laterais Modelo mede 1,76M e veste tamanho 36 A cor do produto nas fotos produzidas com modelos pode sofrer alteração em decorrência do uso do flashVer mais",
    "imagem": "https://shoulder.vtexassets.com/arquivos/ids/2346032/242011913_0079_070-BLUSA-RETA-DECOTE-V.jpg?v=638551916379300000"
}