{
    "marca": "Shoulder",
    "catalogo": "Calcas",
    "nome": "Calça são paulo",
    "url": "https://www.shoulder.com.br/calca-sao-paulo-012420819004/p",
    "preco_original": "R$459,00",
    "preco_final": "R$459,00",
    "breadcrumbs": "coleção calças",
    "descricao": "Calça Comprimento longo Cintura alta Modelagem slim Tecido: Crepe texturizado com fundo acetinado Fechamento frontal com zíper, colchete e botão interno Faixa removível Bolsos laterais e costas Pregas frontais Modelo mede 1,76M e veste tamanho 36 A cor do produto nas fotos produzidas com modelos pode sofrer alteração em decorrência do uso do flashVer mais",
    "imagem": "https://shoulder.vtexassets.com/arquivos/ids/2359758/012420819004_0202_070-CALCA-SAO-PAULO.jpg?v=638562646654800000"
}