{
    "marca": "Shoulder",
    "catalogo": "Calcas",
    "nome": "Calça loose fit natural",
    "url": "https://www.shoulder.com.br/calca-loose-fit-natural-232373903/p",
    "preco_original": "R$439,00",
    "preco_final": "R$359,99",
    "breadcrumbs": "coleção calças jeans",
    "descricao": "Calça Comprimento longo Cintura alta Loose fit Tecido: sarja sem elasticidade, com aspecto natural Tecido FABRICADO com algodão mais responsável Fechamento braguilha por zíper e botão de metal Bolsos aplicados Passantes largos Costura contrastante Modelo mede 1,76M e veste tamanho 36 A cor do produto nas fotos produzidas com modelos pode sofrer alteração em DECORRÊNCIA do uso do flashVer mais",
    "imagem": "https://shoulder.vtexassets.com/arquivos/ids/2177181/232373903_0060_080-CALCA-LOOSE-FIT-NATURAL.jpg?v=638283142317830000"
}