{
    "marca": "Shoulder",
    "catalogo": "Macacoes",
    "nome": "Macacão poá carimbo",
    "url": "https://www.shoulder.com.br/macacao-poa-carimbo-241132001/p",
    "preco_original": "R$699,00",
    "preco_final": "R$559,99",
    "breadcrumbs": "coleção macacões",
    "descricao": "Macacão Comprimento longo Manga longa Modelagem slim Tecido:Crepe leve Decote V Elástico na cintura e no punho Faixa para amarração Fechamento com botões no decote frente Bolsos laterais e costas Modelo mede 1,76M e veste tamanho 36 A cor do produto nas fotos produzidas com modelos pode sofrer alteração em decorrência do uso do flashVer mais",
    "imagem": "https://shoulder.vtexassets.com/arquivos/ids/2276069/241132001_1023_070-MACACAO-POA-CARIMBO.jpg?v=638457911406630000"
}