{
    "marca": "Shoulder",
    "catalogo": "Camisetas",
    "nome": "T-shirt bordado xadrez paetê",
    "url": "https://www.shoulder.com.br/t-shirt-bordado-xadrez-paete-241405003/p",
    "preco_original": "R$339,00",
    "preco_final": "R$259,99",
    "breadcrumbs": "coleção camisetas",
    "descricao": "Camiseta Comprimento médio Manga curta Modelagem boxy Tecido:  Malha fresquinha com toque suave e confortável, se olharmos de perto têm a construção  do TRICOT artesanal, mas com a maleabilidade e elasticidade da malha.  Decote redondo Bordado máquina em linha e lantejoula Manga travetada Modelo mede 1,76M e veste tamanho 36 A cor do produto nas fotos produzidas com modelos pode sofrer alteração em DECORRÊNCIA do uso do flashVer mais",
    "imagem": "https://shoulder.vtexassets.com/arquivos/ids/2360200/241405003_0699_060-T-SHIRT-BORDADO-XADREZ-PAETE.jpg?v=638563043975100000"
}