{
    "marca": "Shoulder",
    "catalogo": "Camisetas",
    "nome": "T-shirt aquarela pincelada",
    "url": "https://www.shoulder.com.br/t-shirt-aquarela-pincelada-241403001/p",
    "preco_original": "R$179,00",
    "preco_final": "R$129,99",
    "breadcrumbs": "coleção camisetas",
    "descricao": "Camiseta Comprimento longo Manga curta Modelagem boxy Tecido: Malha fresquinha com toque suave e confortável, se olharmos de perto têm a construção do TRICOT artesanal, mas com a maleabilidade e elasticidade da malha. Gola alta Viscose de reflorestamento Estampa aquarelada Modelo mede 1,76M e veste tamanho 36 A cor do produto nas fotos produzidas com modelos pode sofrer alteração em DECORRÊNCIA do uso do flashVer mais",
    "imagem": "https://shoulder.vtexassets.com/arquivos/ids/2279070/241403001_0079_080-T-SHIRT-AQUARELA-PINCELADA.jpg?v=638458514076770000"
}